LICENSE
geobatchpy/__init__.py
geobatchpy/batch.py
geobatchpy/boundaries.py
geobatchpy/cli.py
geobatchpy/client.py
geobatchpy/utils.py
geobatchpy-0.2.3.dist-info/entry_points.txt
geobatchpy-0.2.3.dist-info/LICENSE
geobatchpy-0.2.3.dist-info/WHEEL
geobatchpy-0.2.3.dist-info/METADATA
geobatchpy-0.2.3.dist-info/RECORD
