Metadata-Version: 2.1
Name: geobatchpy
Version: 0.2.3
Summary: A CLI and Python Client for the Geoapify API.
Home-page: https://github.com/huels-originals/geobatchpy
License: MIT
Keywords: geoapify,geocoding,openstreetmap,geojson
Author: Paul Kinsvater
Author-email: paul.kinsvater@gmail.com
Requires-Python: >=3.7.1,<4.0
Classifier: License :: OSI Approved :: MIT License
Classifier: Programming Language :: Python :: 3
Classifier: Programming Language :: Python :: 3.10
Classifier: Programming Language :: Python :: 3.8
Classifier: Programming Language :: Python :: 3.9
Requires-Dist: click (>=8.1.3,<9.0.0)
Requires-Dist: requests (>=2.28.1,<3.0.0)
Project-URL: Repository, https://github.com/huels-originals/geobatchpy
